connect_db/__init__.py
connect_db/dependencies.py
connect_db/repository.py
connect_db/session.py
bcl32_connect_db-0.1.0.dist-info/METADATA
bcl32_connect_db-0.1.0.dist-info/WHEEL
bcl32_connect_db-0.1.0.dist-info/top_level.txt
bcl32_connect_db-0.1.0.dist-info/RECORD
